wayland/__about__.py
wayland/__init__.py
wayland/__init__.pyi
wayland/__main__.py
wayland/constants.py
wayland/log.py
wayland/parser.py
wayland/protocols.json
wayland/proxy.py
wayland/state.py
wayland/typehint.py
wayland/unixsocket.py
wayland/hyprland-protocols/protocols/hyprland-ctm-control-v1.xml
wayland/hyprland-protocols/protocols/hyprland-focus-grab-v1.xml
wayland/hyprland-protocols/protocols/hyprland-global-shortcuts-v1.xml
wayland/hyprland-protocols/protocols/hyprland-lock-notify-v1.xml
wayland/hyprland-protocols/protocols/hyprland-surface-v1.xml
wayland/hyprland-protocols/protocols/hyprland-toplevel-export-v1.xml
python_wayland_extra-0.7.0.dist-info/METADATA
python_wayland_extra-0.7.0.dist-info/WHEEL
python_wayland_extra-0.7.0.dist-info/licenses/LICENSE
python_wayland_extra-0.7.0.dist-info/RECORD
