Metadata-Version: 2.4
Name: python-wayland-extra
Version: 0.7.0
Summary: An implementation of the Wayland & Hyprland protocols with no external dependencies. A Python replacement for libwayland, not a wrapper for it.
Project-URL: Homepage, https://github.com/dennisrijsdijk/python-wayland-extra
Project-URL: Documentation, https://github.com/dennisrijsdijk/python-wayland-extra#readme
Project-URL: Issues, https://github.com/dennisrijsdijk/python-wayland-extra/issues
Project-URL: Source, https://github.com/dennisrijsdijk/python-wayland-extra
Project-URL: Changelog, https://github.com/dennisrijsdijk/python-wayland-extra/blob/main/CHANGELOG.md
Author-email: Graham King <grking.email@gmail.com>, Dennis Rijsdijk <hello@dennis.gg>
License: MIT License
License-File: LICENSE
Classifier: Development Status :: 3 - Alpha
Classifier: Intended Audience :: Developers
Classifier: License :: OSI Approved :: MIT License
Classifier: Programming Language :: Python
Classifier: Programming Language :: Python :: 3.8
Classifier: Programming Language :: Python :: 3.9
Classifier: Programming Language :: Python :: 3.10
Classifier: Programming Language :: Python :: 3.11
Classifier: Programming Language :: Python :: 3.12
Classifier: Programming Language :: Python :: Implementation :: CPython
Requires-Python: >=3.8
Provides-Extra: build
Requires-Dist: lxml; extra == 'build'
Requires-Dist: requests; extra == 'build'
